tele_sendtime/__init__.py
tele_sendtime/sendtime/__init__.py
tele_sendtime/sendtime/automation.py
tele_sendtime/sendtime/threads.py
tele_sendtime/sendtime/utils.py
tele_sendtime/telegram/__init__.py
tele_sendtime/telegram/bot.py
tele_sendtime/telegram/utils.py
TeleSendTime-0.1.2.dist-info/LICENSE
TeleSendTime-0.1.2.dist-info/METADATA
TeleSendTime-0.1.2.dist-info/WHEEL
TeleSendTime-0.1.2.dist-info/top_level.txt
TeleSendTime-0.1.2.dist-info/RECORD
