Metadata-Version: 2.1
Name: TeleSendTime
Version: 0.1.2
Summary: Telegram Message Automation Module.
Home-page: https://gitlab.com/DarkSuniuM/TeleSendTime
Author: Alireza Ayinmehr
Author-email: alireza.ayinmehr@gmail.com
License: UNKNOWN
Project-URL: Code, https://gitlab.com/DarkSuniuM/TeleSendTime
Project-URL: Issue tracker, https://gitlab.com/DarkSuniuM/TeleSendTime/issues
Platform: UNKNOWN
Requires-Dist: requests (>=2)
